arkagent_mcp_service/__init__.py
arkagent_mcp_service/server.py
arkagent_mcp_service-0.1.0.dist-info/METADATA
arkagent_mcp_service-0.1.0.dist-info/WHEEL
arkagent_mcp_service-0.1.0.dist-info/entry_points.txt
arkagent_mcp_service-0.1.0.dist-info/RECORD
