Metadata-Version: 2.4
Name: arkagent-mcp-service
Version: 0.1.0
Summary: arkagent mcp server
Author-email: zhendongchen <zhendongchen@emotibot.com>
Requires-Python: >=3.12
Requires-Dist: mcp>=1.4.1
Requires-Dist: requests>=2.32.3
